{
  "name" : "TbSpecification",
  "originTableName" : "tb_specification",
  "comment" : null,
  "fullColumn" : [ {
    "name" : "id",
    "comment" : null,
    "type" : null,
    "shortType" : null,
    "ktShortType" : "Long",
    "custom" : false,
    "ext" : { }
  }, {
    "name" : "specName",
    "comment" : null,
    "type" : null,
    "shortType" : null,
    "ktShortType" : "String",
    "custom" : false,
    "ext" : { }
  } ],
  "pkColumn" : null,
  "otherColumn" : null,
  "savePackageName" : "com.supermarket.pojo",
  "savePath" : "./supermarket_pojo/src/main/java/com/supermarket/pojo",
  "saveModelName" : "supermarket_pojo"
}